pytcherplants/__init__.py
pytcherplants/cli.py
pytcherplants/colors.py
pytcherplants/gpoints.py
pytcherplants/ilastik.py
pytcherplants/utils.py
pytcherplants/tests/__init__.py
pytcherplants/tests/test_colors.py
pytcherplants-0.0.1.dist-info/METADATA
pytcherplants-0.0.1.dist-info/WHEEL
pytcherplants-0.0.1.dist-info/entry_points.txt
pytcherplants-0.0.1.dist-info/top_level.txt
pytcherplants-0.0.1.dist-info/RECORD
