Metadata-Version: 2.1
Name: pytcherplants
Version: 0.0.1
Summary: pitcher geometry & color analysis for top-down images of Sarracenia 
Home-page: https://github.com/w-bonelli/pytcherplants
Author: Wes Bonelli
Author-email: wbonelli@uga.edu
License: BSD-3-Clause
Platform: UNKNOWN
Requires-Python: >=3.6.8
Requires-Dist: requests
Requires-Dist: httpx
Requires-Dist: click
Requires-Dist: tenacity
Requires-Dist: tqdm
Requires-Dist: pytest
Requires-Dist: pytest-dotenv
Requires-Dist: pytest-asyncio
